mass_mailing/__init__.py
mass_mailing/mass_mailing.py
mass_mailing_light22-1.0.0.dist-info/LICENSE
mass_mailing_light22-1.0.0.dist-info/METADATA
mass_mailing_light22-1.0.0.dist-info/WHEEL
mass_mailing_light22-1.0.0.dist-info/top_level.txt
mass_mailing_light22-1.0.0.dist-info/RECORD
