Metadata-Version: 2.1
Name: mass-mailing-light22
Version: 1.0.0
Summary: 邮件群发
Home-page: https://github.com/18513233125/mass_mailing
Download-URL: https://pypi.org/project/mass-mailing-light22
Author: 北极星光
Author-email: light22@126.com
License: MIT
Classifier: Programming Language :: Python :: 3
Classifier: License :: OSI Approved :: MIT License
Classifier: Operating System :: OS Independent
Requires-Python: >=3.6
License-File: LICENSE
